<?xml version="1.0" encoding="UTF-8"?><kml xmlns="http://www.opengis.net/kml/2.2"><Document><Folder><name>Outage Areas</name>
<Placemark><name>11071</name><ExtendedData><Data name="StartUTC"><value>2025-07-26T21:05:05.0000000+00:00</value></Data><Data name="Cause"><value>Equipment Failure</value></Data><Data name="EstCustomersOut"><value>10</value></Data><Data name="UploadTimestampUTC"><value>2025-07-26T22:49:02.0000000+00:00</value></Data><Data name="EstimatedRestorationUTC"><value>2025-07-27T02:45:00.0000000+00:00</value></Data><Data name="OutageStatus"><value>Crew assigned for repairs</value></Data><Data name="IsStormModeData"><value>False</value></Data><Data name="DistrictBroadcastMessages"><value>[]</value></Data><Data name="RegionBroadcastMessages"><value>[]</value></Data><Data name="IncidentBroadcastMessages"><value>[]</value></Data></ExtendedData><Polygon xmlns="http://www.opengis.net/kml/2.2">
  <outerBoundaryIs>
    <LinearRing>
      <coordinates>-122.30330315564,47.8283222314265,0 -122.297858962007,47.8282842487491,0 -122.292414776381,47.8282460067196,0 -122.292463186502,47.8318892063678,0 -122.292511603431,47.8355324048219,0 -122.297948958393,47.8355546792561,0 -122.303386318004,47.8355766950251,0 -122.303344733912,47.8319494638152,0 -122.30330315564,47.8283222314265,0 </coordinates>
    </LinearRing>
  </outerBoundaryIs>
</Polygon></Placemark>
<Placemark><name>10754</name><ExtendedData><Data name="StartUTC"><value>2025-07-26T20:14:43.0000000+00:00</value></Data><Data name="Cause"><value>Pending Investigation</value></Data><Data name="EstCustomersOut"><value>1</value></Data><Data name="UploadTimestampUTC"><value>2025-07-26T22:49:02.0000000+00:00</value></Data><Data name="EstimatedRestorationUTC"><value>We’re re-evaluating estimated restoration time, thanks for your patience.</value></Data><Data name="OutageStatus"><value>We're investigating</value></Data><Data name="IsStormModeData"><value>False</value></Data><Data name="DistrictBroadcastMessages"><value>[]</value></Data><Data name="RegionBroadcastMessages"><value>[]</value></Data><Data name="IncidentBroadcastMessages"><value>[]</value></Data></ExtendedData><Polygon xmlns="http://www.opengis.net/kml/2.2">
  <outerBoundaryIs>
    <LinearRing>
      <coordinates>-122.066189470896,47.9277083669715,0 -122.060833857914,47.9277063109753,0 -122.055478245383,47.9277040044817,0 -122.055647340806,47.9313418034681,0 -122.055816460019,47.9349796006375,0 -122.06110799959,47.9349570449381,0 -122.06639953452,47.9349342447339,0 -122.06629449537,47.9313213066738,0 -122.066189470896,47.9277083669715,0 </coordinates>
    </LinearRing>
  </outerBoundaryIs>
</Polygon></Placemark>
</Folder></Document></kml>
