<?xml version="1.0" encoding="UTF-8"?><kml xmlns="http://www.opengis.net/kml/2.2"><Document><Folder><name>Outage Areas</name>
<Placemark><name>7280</name><ExtendedData><Data name="StartUTC"><value>2025-10-15T19:40:59.0000000+00:00</value></Data><Data name="Cause"><value>Pending Investigation</value></Data><Data name="EstCustomersOut"><value>11</value></Data><Data name="UploadTimestampUTC"><value>2025-10-15T19:44:02.0000000+00:00</value></Data><Data name="EstimatedRestorationUTC"><value>2025-10-15T21:45:00.0000000+00:00</value></Data><Data name="OutageStatus"><value>Outage Reported</value></Data><Data name="IsStormModeData"><value>False</value></Data><Data name="DistrictBroadcastMessages"><value>[]</value></Data><Data name="RegionBroadcastMessages"><value>[]</value></Data><Data name="IncidentBroadcastMessages"><value>[]</value></Data></ExtendedData><Polygon xmlns="http://www.opengis.net/kml/2.2">
  <outerBoundaryIs>
    <LinearRing>
      <coordinates>-122.001435480856,48.0719300140129,0 -121.996017111448,48.0719028691913,0 -121.99059874777,48.0718754686874,0 -121.990703004775,48.0755864770355,0 -121.990807276785,48.0792974830573,0 -121.996102502741,48.0793523811799,0 -122.001397739946,48.0794070351444,0 -122.001416611769,48.0756685257128,0 -122.001435480856,48.0719300140129,0 </coordinates>
    </LinearRing>
  </outerBoundaryIs>
</Polygon></Placemark>
<Placemark><name>7975</name><ExtendedData><Data name="StartUTC"><value>2025-10-15T19:40:59.0000000+00:00</value></Data><Data name="Cause"><value>Pending Investigation</value></Data><Data name="EstCustomersOut"><value>15</value></Data><Data name="UploadTimestampUTC"><value>2025-10-15T19:44:02.0000000+00:00</value></Data><Data name="EstimatedRestorationUTC"><value>2025-10-15T21:45:00.0000000+00:00</value></Data><Data name="OutageStatus"><value>Outage Reported</value></Data><Data name="IsStormModeData"><value>False</value></Data><Data name="DistrictBroadcastMessages"><value>[]</value></Data><Data name="RegionBroadcastMessages"><value>[]</value></Data><Data name="IncidentBroadcastMessages"><value>[]</value></Data></ExtendedData><Polygon xmlns="http://www.opengis.net/kml/2.2">
  <outerBoundaryIs>
    <LinearRing>
      <coordinates>-121.979887853014,48.0794773073346,0 -121.980028970469,48.0831345050319,0 -121.980170107942,48.0867917003578,0 -121.985507269671,48.0866985286185,0 -121.990844412086,48.0866051088746,0 -121.99082584312,48.082951297064,0 -121.990807276785,48.0792974830573,0 -121.985347574419,48.0793875249772,0 -121.979887853014,48.0794773073346,0 </coordinates>
    </LinearRing>
  </outerBoundaryIs>
</Polygon></Placemark>
<Placemark><name>7974</name><ExtendedData><Data name="StartUTC"><value>2025-10-15T19:40:59.0000000+00:00</value></Data><Data name="Cause"><value>Pending Investigation</value></Data><Data name="EstCustomersOut"><value>45</value></Data><Data name="UploadTimestampUTC"><value>2025-10-15T19:44:02.0000000+00:00</value></Data><Data name="EstimatedRestorationUTC"><value>2025-10-15T21:45:00.0000000+00:00</value></Data><Data name="OutageStatus"><value>Outage Reported</value></Data><Data name="IsStormModeData"><value>False</value></Data><Data name="DistrictBroadcastMessages"><value>[]</value></Data><Data name="RegionBroadcastMessages"><value>[]</value></Data><Data name="IncidentBroadcastMessages"><value>[]</value></Data></ExtendedData><Polygon xmlns="http://www.opengis.net/kml/2.2">
  <outerBoundaryIs>
    <LinearRing>
      <coordinates>-122.001397739946,48.0794070351444,0 -121.996102502741,48.0793523811799,0 -121.990807276785,48.0792974830573,0 -121.99082584312,48.082951297064,0 -121.990844412086,48.0866051088746,0 -121.996237752194,48.0866500018487,0 -122.001631101667,48.0866946415693,0 -122.001514412561,48.0830508395069,0 -122.001397739946,48.0794070351444,0 </coordinates>
    </LinearRing>
  </outerBoundaryIs>
</Polygon></Placemark>
<Placemark><name>7610</name><ExtendedData><Data name="StartUTC"><value>2025-10-15T18:34:58.9815081+00:00</value></Data><Data name="Cause"><value>Equipment Failure</value></Data><Data name="EstCustomersOut"><value>2</value></Data><Data name="UploadTimestampUTC"><value>2025-10-15T19:44:02.0000000+00:00</value></Data><Data name="EstimatedRestorationUTC"><value>2025-10-15T21:30:00.0000000+00:00</value></Data><Data name="OutageStatus"><value>We're investigating</value></Data><Data name="IsStormModeData"><value>False</value></Data><Data name="DistrictBroadcastMessages"><value>[]</value></Data><Data name="RegionBroadcastMessages"><value>[]</value></Data><Data name="IncidentBroadcastMessages"><value>[]</value></Data></ExtendedData><Polygon xmlns="http://www.opengis.net/kml/2.2">
  <outerBoundaryIs>
    <LinearRing>
      <coordinates>-122.135098142741,48.0919562172663,0 -122.129704402641,48.091985485164,0 -122.129724258653,48.0956822596672,0 -122.129744117513,48.0993790318693,0 -122.135174075166,48.0992712568749,0 -122.140604010088,48.0991632252399,0 -122.140547939455,48.0955449617863,0 -122.140491876691,48.0919266961048,0 -122.135098142741,48.0919562172663,0 </coordinates>
    </LinearRing>
  </outerBoundaryIs>
</Polygon></Placemark>
</Folder></Document></kml>
