<?xml version="1.0" encoding="UTF-8"?><kml xmlns="http://www.opengis.net/kml/2.2"><Document><Folder><name>Outage Areas</name>
<Placemark><name>12474</name><ExtendedData><Data name="StartUTC"><value>2025-06-26T21:04:16.0000000+00:00</value></Data><Data name="Cause"><value>Miscellaneous</value></Data><Data name="EstCustomersOut"><value>1</value></Data><Data name="UploadTimestampUTC"><value>2025-06-26T22:55:03.0000000+00:00</value></Data><Data name="EstimatedRestorationUTC"><value>2025-06-27T02:15:00.0000000+00:00</value></Data><Data name="OutageStatus"><value>Crew assigned for repairs</value></Data><Data name="IsStormModeData"><value>False</value></Data><Data name="DistrictBroadcastMessages"><value>[]</value></Data><Data name="RegionBroadcastMessages"><value>[]</value></Data><Data name="IncidentBroadcastMessages"><value>[]</value></Data></ExtendedData><Polygon xmlns="http://www.opengis.net/kml/2.2">
  <outerBoundaryIs>
    <LinearRing>
      <coordinates>-122.033875180651,47.7831107636197,0 -122.02868214078,47.7830193540133,0 -122.023489119236,47.7829277082248,0 -122.023478612365,47.7865317127387,0 -122.023468104033,47.7901357162806,0 -122.028751638315,47.7903105171128,0 -122.03403520819,47.79048507349,0 -122.033955188732,47.7867979190915,0 -122.033875180651,47.7831107636197,0 </coordinates>
    </LinearRing>
  </outerBoundaryIs>
</Polygon></Placemark>
<Placemark><name>9583</name><ExtendedData><Data name="StartUTC"><value>2025-06-26T15:42:19.8038738+00:00</value></Data><Data name="Cause"><value>Miscellaneous</value></Data><Data name="EstCustomersOut"><value>1</value></Data><Data name="UploadTimestampUTC"><value>2025-06-26T22:55:03.0000000+00:00</value></Data><Data name="EstimatedRestorationUTC"><value>2025-06-26T23:45:00.0000000+00:00</value></Data><Data name="OutageStatus"><value>Outage Reported</value></Data><Data name="IsStormModeData"><value>False</value></Data><Data name="DistrictBroadcastMessages"><value>[]</value></Data><Data name="RegionBroadcastMessages"><value>[]</value></Data><Data name="IncidentBroadcastMessages"><value>[]</value></Data></ExtendedData><Polygon xmlns="http://www.opengis.net/kml/2.2">
  <outerBoundaryIs>
    <LinearRing>
      <coordinates>-122.065377810663,48.0082392471431,0 -122.05994710292,48.0081508936341,0 -122.054516221576,48.0080622754076,0 -122.054584783448,48.0117489731634,0 -122.054653355112,48.0154356689382,0 -122.059916596535,48.0154889586838,0 -122.065179848797,48.0155420069108,0 -122.065220402894,48.0140475987019,0 -122.065254092418,48.0128060822156,0 -122.065281890976,48.0117800193786,0 -122.065377810663,48.0082392471431,0 </coordinates>
    </LinearRing>
  </outerBoundaryIs>
</Polygon></Placemark>
</Folder></Document></kml>
