<?xml version="1.0" encoding="UTF-8"?><kml xmlns="http://www.opengis.net/kml/2.2"><Document><Folder><name>Outage Areas</name>
<Placemark><name>7916</name><ExtendedData><Data name="StartUTC"><value>2025-07-14T04:37:34.0000000+00:00</value></Data><Data name="Cause"><value>Pending Investigation</value></Data><Data name="EstCustomersOut"><value>1</value></Data><Data name="UploadTimestampUTC"><value>2025-07-14T05:18:04.0000000+00:00</value></Data><Data name="EstimatedRestorationUTC"><value>2025-07-14T06:45:00.0000000+00:00</value></Data><Data name="OutageStatus"><value>We're investigating</value></Data><Data name="IsStormModeData"><value>False</value></Data><Data name="DistrictBroadcastMessages"><value>[]</value></Data><Data name="RegionBroadcastMessages"><value>[]</value></Data><Data name="IncidentBroadcastMessages"><value>[]</value></Data></ExtendedData><Polygon xmlns="http://www.opengis.net/kml/2.2">
  <outerBoundaryIs>
    <LinearRing>
      <coordinates>-121.802407423839,48.093868976376,0 -121.797078959524,48.0939080969308,0 -121.797102705202,48.0975059368093,0 -121.797126454194,48.1011037744994,0 -121.802482304629,48.1010545888738,0 -121.807838144818,48.1010051535745,0 -121.807787008871,48.0974173822139,0 -121.807735880041,48.0938296086596,0 -121.802407423839,48.093868976376,0 </coordinates>
    </LinearRing>
  </outerBoundaryIs>
</Polygon></Placemark>
</Folder></Document></kml>
