<?xml version="1.0" encoding="UTF-8"?><kml xmlns="http://www.opengis.net/kml/2.2"><Document><Folder><name>Outage Areas</name>
<Placemark><name>8746</name><ExtendedData><Data name="StartUTC"><value>2025-05-22T12:51:09.0000000+00:00</value></Data><Data name="Cause"><value>Pending Investigation</value></Data><Data name="EstCustomersOut"><value>8</value></Data><Data name="UploadTimestampUTC"><value>2025-05-22T13:06:03.0000000+00:00</value></Data><Data name="EstimatedRestorationUTC"><value>2025-05-22T15:00:00.0000000+00:00</value></Data><Data name="OutageStatus"><value>Outage Reported</value></Data><Data name="IsStormModeData"><value>False</value></Data><Data name="DistrictBroadcastMessages"><value>[]</value></Data><Data name="RegionBroadcastMessages"><value>[]</value></Data><Data name="IncidentBroadcastMessages"><value>[]</value></Data></ExtendedData><Polygon xmlns="http://www.opengis.net/kml/2.2">
  <outerBoundaryIs>
    <LinearRing>
      <coordinates>-122.239016501644,47.9073547393914,0 -122.233623894007,47.907377334052,0 -122.228231281686,47.9073996746419,0 -122.228241523806,47.9110400250732,0 -122.228251767367,47.9146803740155,0 -122.23366189399,47.9146472339856,0 -122.239072013654,47.9146138382682,0 -122.239044255702,47.9109842895728,0 -122.239016501644,47.9073547393914,0 </coordinates>
    </LinearRing>
  </outerBoundaryIs>
</Polygon></Placemark>
</Folder></Document></kml>
