<?xml version="1.0" encoding="UTF-8"?><kml xmlns="http://www.opengis.net/kml/2.2"><Document><Folder><name>Outage Areas</name>
<Placemark><name>9175</name><ExtendedData><Data name="StartUTC"><value>2025-04-23T16:15:44.0000000+00:00</value></Data><Data name="Cause"><value>Equipment Failure</value></Data><Data name="EstCustomersOut"><value>2</value></Data><Data name="UploadTimestampUTC"><value>2025-04-23T19:36:03.0000000+00:00</value></Data><Data name="EstimatedRestorationUTC"><value>2025-04-23T21:00:00.0000000+00:00</value></Data><Data name="OutageStatus"><value>Crew assigned for repairs</value></Data><Data name="IsStormModeData"><value>False</value></Data><Data name="DistrictBroadcastMessages"><value>[]</value></Data><Data name="RegionBroadcastMessages"><value>[]</value></Data><Data name="IncidentBroadcastMessages"><value>[]</value></Data></ExtendedData><Polygon xmlns="http://www.opengis.net/kml/2.2">
  <outerBoundaryIs>
    <LinearRing>
      <coordinates>-122.032228412324,48.0577871576384,0 -122.027190333112,48.0576785827246,0 -122.022152275127,48.0575697866967,0 -122.02179335805,48.0611533591566,0 -122.021434391104,48.0647369284692,0 -122.026794719493,48.0648850976959,0 -122.03215507865,48.0650330166493,0 -122.032191748062,48.0614100881851,0 -122.032228412324,48.0577871576384,0 </coordinates>
    </LinearRing>
  </outerBoundaryIs>
</Polygon></Placemark>
<Placemark><name>10337</name><ExtendedData><Data name="StartUTC"><value>2025-04-23T18:39:11.0000000+00:00</value></Data><Data name="Cause"><value>Pending Investigation</value></Data><Data name="EstCustomersOut"><value>1</value></Data><Data name="UploadTimestampUTC"><value>2025-04-23T19:36:03.0000000+00:00</value></Data><Data name="EstimatedRestorationUTC"><value>2025-04-23T20:45:00.0000000+00:00</value></Data><Data name="OutageStatus"><value>Outage Reported</value></Data><Data name="IsStormModeData"><value>False</value></Data><Data name="DistrictBroadcastMessages"><value>[]</value></Data><Data name="RegionBroadcastMessages"><value>[]</value></Data><Data name="IncidentBroadcastMessages"><value>[]</value></Data></ExtendedData><Polygon xmlns="http://www.opengis.net/kml/2.2">
  <outerBoundaryIs>
    <LinearRing>
      <coordinates>-122.282179905826,47.8930585298207,0 -122.276736968851,47.8930451373633,0 -122.271294034719,47.8930314859988,0 -122.271329317683,47.8966561322982,0 -122.271364605589,47.9002807771684,0 -122.276802050593,47.9002943310572,0 -122.282239498418,47.9003076265974,0 -122.282209700035,47.8966830789221,0 -122.282179905826,47.8930585298207,0 </coordinates>
    </LinearRing>
  </outerBoundaryIs>
</Polygon></Placemark>
<Placemark><name>8454</name><ExtendedData><Data name="StartUTC"><value>2025-04-23T18:48:05.0000000+00:00</value></Data><Data name="Cause"><value>Pending Investigation</value></Data><Data name="EstCustomersOut"><value>2</value></Data><Data name="UploadTimestampUTC"><value>2025-04-23T19:36:03.0000000+00:00</value></Data><Data name="EstimatedRestorationUTC"><value>2025-04-23T21:00:00.0000000+00:00</value></Data><Data name="OutageStatus"><value>We're investigating</value></Data><Data name="IsStormModeData"><value>False</value></Data><Data name="DistrictBroadcastMessages"><value>[]</value></Data><Data name="RegionBroadcastMessages"><value>[]</value></Data><Data name="IncidentBroadcastMessages"><value>[]</value></Data></ExtendedData><Polygon xmlns="http://www.opengis.net/kml/2.2">
  <outerBoundaryIs>
    <LinearRing>
      <coordinates>-122.205612881111,48.1082462750985,0 -122.200254422737,48.1080016892289,0 -122.194896015246,48.1077568534684,0 -122.194580404522,48.1114828432189,0 -122.194809631087,48.1152370244081,0 -122.200155620936,48.1154502909203,0 -122.205498957909,48.1156632013322,0 -122.205554218236,48.1119531220976,0 -122.205612881111,48.1082462750985,0 </coordinates>
    </LinearRing>
  </outerBoundaryIs>
</Polygon></Placemark>
<Placemark><name>50144595</name><ExtendedData><Data name="StartUTC"><value>2025-04-23T19:23:52.0000000+00:00</value></Data><Data name="Cause"><value>Pending Investigation</value></Data><Data name="EstCustomersOut"><value>2</value></Data><Data name="UploadTimestampUTC"><value>2025-04-23T19:36:03.0000000+00:00</value></Data><Data name="EstimatedRestorationUTC"><value>2025-04-23T21:30:00.0000000+00:00</value></Data><Data name="OutageStatus"><value>We're investigating</value></Data><Data name="IsStormModeData"><value>False</value></Data><Data name="DistrictBroadcastMessages"><value>[]</value></Data><Data name="RegionBroadcastMessages"><value>[]</value></Data><Data name="IncidentBroadcastMessages"><value>[]</value></Data></ExtendedData><Polygon xmlns="http://www.opengis.net/kml/2.2">
  <outerBoundaryIs>
    <LinearRing>
      <coordinates>-122.515676577574,48.2185827022642,0 -122.515573853753,48.2257851036466,0 -122.515763833533,48.225788512255,0 -122.521143241697,48.2258518282219,0 -122.526522664068,48.2259148924116,0 -122.52652105672,48.2222392134718,0 -122.526519480531,48.2186330018544,0 -122.515676577574,48.2185827022642,0 </coordinates>
    </LinearRing>
  </outerBoundaryIs>
</Polygon></Placemark>
</Folder></Document></kml>
